point_in_poly/__init__.py
point_in_poly/point_in_poly.py
point_in_poly-0.1.0.dist-info/LICENSE
point_in_poly-0.1.0.dist-info/METADATA
point_in_poly-0.1.0.dist-info/WHEEL
point_in_poly-0.1.0.dist-info/top_level.txt
point_in_poly-0.1.0.dist-info/RECORD
